README.md
setup.py
PyQt6_Fluent_Widgets_TextInputDialog.egg-info/PKG-INFO
PyQt6_Fluent_Widgets_TextInputDialog.egg-info/SOURCES.txt
PyQt6_Fluent_Widgets_TextInputDialog.egg-info/dependency_links.txt
PyQt6_Fluent_Widgets_TextInputDialog.egg-info/requires.txt
PyQt6_Fluent_Widgets_TextInputDialog.egg-info/top_level.txt
qfluentwidgets_textinputdialog/__init__.py
qfluentwidgets_textinputdialog/text_input_dialog.py