Metadata-Version: 2.1
Name: PyQt6-Fluent-Widgets-TextInputDialog
Version: 0.0.2
Summary: It provides a simple way to create text input dialogs.
Author: Chamiko
Author-email: Chamiko@foxmail.com
Keywords: PyQt6,Fluent-Widgets
Classifier: Development Status :: 1 - Planning
Requires-Python: >=3.6, <3.12
Requires-Dist: PyQt6-Fluent-Widgets
